{
  "stock_words": [
    {
      "word": "That's",
      "start": 0.976,
      "end": 1.16,
      "duration": 0.18399999999999994
    },
    {
      "word": "why",
      "start": 1.18,
      "end": 1.302,
      "duration": 0.12200000000000011
    },
    {
      "word": "he's",
      "start": 1.323,
      "end": 1.466,
      "duration": 0.14300000000000002
    },
    {
      "word": "so",
      "start": 1.486,
      "end": 1.609,
      "duration": 0.123
    },
    {
      "word": "fucking",
      "start": 1.649,
      "end": 1.956,
      "duration": 0.30699999999999994
    },
    {
      "word": "famous",
      "start": 1.976,
      "end": 2.302,
      "duration": 0.32600000000000007
    },
    {
      "word": "bro.",
      "start": 2.323,
      "end": 2.996,
      "duration": 0.673
    },
    {
      "word": "That's",
      "start": 2.976,
      "end": 3.833,
      "duration": 0.8570000000000002
    },
    {
      "word": "why",
      "start": 3.874,
      "end": 3.956,
      "duration": 0.08199999999999985
    },
    {
      "word": "Gordon",
      "start": 4.037,
      "end": 4.302,
      "duration": 0.2649999999999997
    },
    {
      "word": "Ramsay's",
      "start": 4.343,
      "end": 4.629,
      "duration": 0.2859999999999996
    },
    {
      "word": "so",
      "start": 4.649,
      "end": 4.813,
      "duration": 0.1639999999999997
    },
    {
      "word": "famous.",
      "start": 4.854,
      "end": 4.996,
      "duration": 0.14200000000000035
    },
    {
      "word": "Oh,",
      "start": 4.976,
      "end": 5.288,
      "duration": 0.3120000000000003
    },
    {
      "word": "everyone.",
      "start": 5.684,
      "end": 5.997,
      "duration": 0.3129999999999997
    },
    {
      "word": "Because",
      "start": 5.976,
      "end": 6.262,
      "duration": 0.2859999999999996
    },
    {
      "word": "he's",
      "start": 6.323,
      "end": 6.486,
      "duration": 0.16299999999999937
    },
    {
      "word": "only",
      "start": 6.507,
      "end": 6.588,
      "duration": 0.0810000000000004
    },
    {
      "word": "one",
      "start": 6.609,
      "end": 6.67,
      "duration": 0.06099999999999994
    },
    {
      "word": "over",
      "start": 6.731,
      "end": 6.813,
      "duration": 0.08199999999999985
    },
    {
      "word": "there",
      "start": 6.833,
      "end": 6.996,
      "duration": 0.16300000000000026
    },
    {
      "word": "who",
      "start": 7.037,
      "end": 7.282,
      "duration": 0.2450000000000001
    },
    {
      "word": "knows",
      "start": 7.323,
      "end": 7.629,
      "duration": 0.30599999999999916
    },
    {
      "word": "how",
      "start": 7.649,
      "end": 7.711,
      "duration": 0.06200000000000028
    },
    {
      "word": "to",
      "start": 7.731,
      "end": 7.772,
      "duration": 0.04100000000000037
    },
    {
      "word": "make",
      "start": 7.792,
      "end": 7.874,
      "duration": 0.08199999999999985
    },
    {
      "word": "food.",
      "start": 7.894,
      "end": 7.996,
      "duration": 0.10200000000000031
    },
    {
      "word": "He's",
      "start": 7.976,
      "end": 9.017,
      "duration": 1.0409999999999995
    },
    {
      "word": "only",
      "start": 9.037,
      "end": 9.119,
      "duration": 0.08199999999999896
    },
    {
      "word": "one",
      "start": 9.139,
      "end": 9.2,
      "duration": 0.06099999999999994
    },
    {
      "word": "over",
      "start": 9.221,
      "end": 9.302,
      "duration": 0.08099999999999952
    },
    {
      "word": "there",
      "start": 9.323,
      "end": 9.425,
      "duration": 0.10200000000000031
    },
    {
      "word": "who",
      "start": 9.445,
      "end": 9.507,
      "duration": 0.06199999999999939
    },
    {
      "word": "knows",
      "start": 9.527,
      "end": 9.629,
      "duration": 0.10200000000000031
    },
    {
      "word": "how",
      "start": 9.649,
      "end": 9.711,
      "duration": 0.062000000000001165
    },
    {
      "word": "to",
      "start": 9.731,
      "end": 9.772,
      "duration": 0.04100000000000037
    },
    {
      "word": "make",
      "start": 9.792,
      "end": 9.874,
      "duration": 0.08200000000000074
    },
    {
      "word": "food.",
      "start": 9.894,
      "end": 9.996,
      "duration": 0.10200000000000031
    },
    {
      "word": "We",
      "start": 9.976,
      "end": 10.302,
      "duration": 0.32599999999999874
    },
    {
      "word": "got",
      "start": 10.915,
      "end": 11.16,
      "duration": 0.245000000000001
    },
    {
      "word": "one.",
      "start": 11.915,
      "end": 11.996,
      "duration": 0.0810000000000013
    },
    {
      "word": "He",
      "start": 11.976,
      "end": 12.772,
      "duration": 0.7959999999999994
    },
    {
      "word": "goes",
      "start": 12.813,
      "end": 13.425,
      "duration": 0.6120000000000001
    },
    {
      "word": "with",
      "start": 13.527,
      "end": 13.609,
      "duration": 0.08200000000000074
    },
    {
      "word": "UK.",
      "start": 13.731,
      "end": 13.996,
      "duration": 0.26500000000000057
    },
    {
      "word": "He",
      "start": 13.976,
      "end": 14.08,
      "duration": 0.1039999999999992
    },
    {
      "word": "goes",
      "start": 14.122,
      "end": 14.288,
      "duration": 0.16600000000000037
    },
    {
      "word": "with",
      "start": 14.33,
      "end": 14.455,
      "duration": 0.125
    },
    {
      "word": "UK.",
      "start": 14.559,
      "end": 14.997,
      "duration": 0.4380000000000006
    },
    {
      "word": "He",
      "start": 14.976,
      "end": 15.503,
      "duration": 0.5269999999999992
    },
    {
      "word": "meets",
      "start": 15.523,
      "end": 15.827,
      "duration": 0.30400000000000027
    },
    {
      "word": "with",
      "start": 16.476,
      "end": 16.78,
      "duration": 0.30400000000000205
    },
    {
      "word": "King",
      "start": 17.064,
      "end": 17.267,
      "duration": 0.2029999999999994
    },
    {
      "word": "Charles.",
      "start": 17.348,
      "end": 17.996,
      "duration": 0.6479999999999997
    },
    {
      "word": "I",
      "start": 17.976,
      "end": 18.098,
      "duration": 0.12199999999999989
    },
    {
      "word": "mean,",
      "start": 18.118,
      "end": 18.3,
      "duration": 0.18200000000000216
    },
    {
      "word": "this",
      "start": 18.321,
      "end": 18.442,
      "duration": 0.12099999999999866
    },
    {
      "word": "is",
      "start": 18.483,
      "end": 18.523,
      "duration": 0.03999999999999915
    },
    {
      "word": "right",
      "start": 18.584,
      "end": 18.726,
      "duration": 0.14199999999999946
    },
    {
      "word": "after",
      "start": 18.787,
      "end": 19.152,
      "duration": 0.365000000000002
    },
    {
      "word": "he",
      "start": 19.577,
      "end": 19.658,
      "duration": 0.08099999999999952
    },
    {
      "word": "got",
      "start": 19.679,
      "end": 19.841,
      "duration": 0.1620000000000026
    },
    {
      "word": "kicked",
      "start": 19.902,
      "end": 20.104,
      "duration": 0.20199999999999818
    },
    {
      "word": "out",
      "start": 20.165,
      "end": 20.226,
      "duration": 0.06099999999999994
    },
    {
      "word": "of",
      "start": 20.246,
      "end": 20.287,
      "duration": 0.04100000000000037
    },
    {
      "word": "the",
      "start": 20.307,
      "end": 20.368,
      "duration": 0.06099999999999994
    },
    {
      "word": "White",
      "start": 20.408,
      "end": 20.571,
      "duration": 0.16300000000000026
    },
    {
      "word": "House.",
      "start": 20.591,
      "end": 20.996,
      "duration": 0.4049999999999976
    },
    {
      "word": "I",
      "start": 20.976,
      "end": 21.098,
      "duration": 0.12199999999999989
    },
    {
      "word": "don't",
      "start": 21.119,
      "end": 21.792,
      "duration": 0.6730000000000018
    },
    {
      "word": "know",
      "start": 21.813,
      "end": 21.894,
      "duration": 0.08099999999999952
    },
    {
      "word": "if",
      "start": 21.915,
      "end": 21.956,
      "duration": 0.04100000000000037
    },
    {
      "word": "I've",
      "start": 21.976,
      "end": 22.058,
      "duration": 0.08200000000000074
    },
    {
      "word": "had",
      "start": 22.078,
      "end": 22.18,
      "duration": 0.10200000000000031
    },
    {
      "word": "to",
      "start": 22.221,
      "end": 22.302,
      "duration": 0.08099999999999952
    },
    {
      "word": "verify",
      "start": 22.364,
      "end": 22.874,
      "duration": 0.509999999999998
    },
    {
      "word": "that.",
      "start": 22.894,
      "end": 22.996,
      "duration": 0.10200000000000031
    },
    {
      "word": "He",
      "start": 23.639,
      "end": 23.823,
      "duration": 0.18400000000000105
    },
    {
      "word": "was",
      "start": 23.844,
      "end": 23.946,
      "duration": 0.10200000000000031
    },
    {
      "word": "kicked",
      "start": 24.008,
      "end": 24.213,
      "duration": 0.20500000000000185
    },
    {
      "word": "out",
      "start": 24.274,
      "end": 24.356,
      "duration": 0.08200000000000074
    },
    {
      "word": "the",
      "start": 24.377,
      "end": 24.479,
      "duration": 0.10200000000000031
    },
    {
      "word": "fucking",
      "start": 24.52,
      "end": 24.786,
      "duration": 0.2660000000000018
    },
    {
      "word": "wayhouse.",
      "start": 24.807,
      "end": 25.34,
      "duration": 0.5330000000000013
    },
    {
      "word": "After",
      "start": 25.319,
      "end": 25.748,
      "duration": 0.42900000000000205
    },
    {
      "word": "that",
      "start": 25.788,
      "end": 25.911,
      "duration": 0.12300000000000111
    },
    {
      "word": "fucking",
      "start": 25.952,
      "end": 26.217,
      "duration": 0.264999999999997
    },
    {
      "word": "meeting,",
      "start": 26.237,
      "end": 26.421,
      "duration": 0.18400000000000105
    },
    {
      "word": "they",
      "start": 26.442,
      "end": 26.523,
      "duration": 0.08099999999999952
    },
    {
      "word": "were",
      "start": 26.605,
      "end": 26.686,
      "duration": 0.08099999999999952
    },
    {
      "word": "both",
      "start": 26.707,
      "end": 26.788,
      "duration": 0.08099999999999952
    },
    {
      "word": "ever...",
      "start": 26.829,
      "end": 27.34,
      "duration": 0.5109999999999992
    },
    {
      "word": "He",
      "start": 27.319,
      "end": 27.542,
      "duration": 0.22300000000000253
    },
    {
      "word": "went",
      "start": 27.684,
      "end": 27.846,
      "duration": 0.16199999999999903
    },
    {
      "word": "on",
      "start": 27.907,
      "end": 27.988,
      "duration": 0.08099999999999952
    },
    {
      "word": "a",
      "start": 28.089,
      "end": 28.11,
      "duration": 0.021000000000000796
    },
    {
      "word": "Brett",
      "start": 28.252,
      "end": 28.474,
      "duration": 0.2220000000000013
    },
    {
      "word": "Bear",
      "start": 28.495,
      "end": 28.697,
      "duration": 0.20199999999999818
    },
    {
      "word": "or",
      "start": 28.718,
      "end": 28.758,
      "duration": 0.03999999999999915
    },
    {
      "word": "somebody",
      "start": 28.9,
      "end": 29.265,
      "duration": 0.365000000000002
    },
    {
      "word": "in",
      "start": 29.285,
      "end": 29.346,
      "duration": 0.06099999999999994
    },
    {
      "word": "half",
      "start": 29.468,
      "end": 29.549,
      "duration": 0.08099999999999952
    },
    {
      "word": "a",
      "start": 29.569,
      "end": 29.589,
      "duration": 0.019999999999999574
    },
    {
      "word": "pile",
      "start": 29.792,
      "end": 29.954,
      "duration": 0.16199999999999903
    },
    {
      "word": "of...",
      "start": 30.015,
      "end": 30.339,
      "duration": 0.32399999999999807
    },
    {
      "word": "Half",
      "start": 30.319,
      "end": 30.572,
      "duration": 0.2530000000000001
    },
    {
      "word": "a",
      "start": 30.593,
      "end": 30.614,
      "duration": 0.021000000000000796
    },
    {
      "word": "pile",
      "start": 30.677,
      "end": 30.909,
      "duration": 0.23199999999999932
    },
    {
      "word": "of",
      "start": 30.93,
      "end": 30.972,
      "duration": 0.04200000000000159
    },
    {
      "word": "jazz.",
      "start": 30.993,
      "end": 31.14,
      "duration": 0.14700000000000202
    },
    {
      "word": "Listen,",
      "start": 31.119,
      "end": 31.469,
      "duration": 0.3500000000000014
    },
    {
      "word": "and",
      "start": 31.572,
      "end": 31.654,
      "duration": 0.08200000000000074
    },
    {
      "word": "dude,",
      "start": 31.695,
      "end": 31.88,
      "duration": 0.18499999999999872
    },
    {
      "word": "real",
      "start": 31.901,
      "end": 32.107,
      "duration": 0.20599999999999952
    },
    {
      "word": "talk.",
      "start": 32.148,
      "end": 32.58,
      "duration": 0.43199999999999505
    },
    {
      "word": "The",
      "start": 32.559,
      "end": 32.764,
      "duration": 0.2050000000000054
    },
    {
      "word": "motherfucker",
      "start": 32.784,
      "end": 33.295,
      "duration": 0.5110000000000028
    },
    {
      "word": "has",
      "start": 33.336,
      "end": 33.418,
      "duration": 0.08200000000000074
    },
    {
      "word": "never",
      "start": 33.48,
      "end": 33.684,
      "duration": 0.20400000000000063
    },
    {
      "word": "said",
      "start": 33.745,
      "end": 33.889,
      "duration": 0.14400000000000546
    },
    {
      "word": "thank",
      "start": 33.93,
      "end": 34.175,
      "duration": 0.24499999999999744
    },
    {
      "word": "you.",
      "start": 34.195,
      "end": 34.38,
      "duration": 0.18500000000000227
    },
    {
      "word": "Ever.",
      "start": 34.359,
      "end": 34.901,
      "duration": 0.5420000000000016
    },
    {
      "word": "He's",
      "start": 34.879,
      "end": 35.204,
      "duration": 0.32500000000000284
    },
    {
      "word": "come",
      "start": 35.325,
      "end": 35.609,
      "duration": 0.2839999999999989
    },
    {
      "word": "here",
      "start": 35.65,
      "end": 35.812,
      "duration": 0.16199999999999903
    },
    {
      "word": "and",
      "start": 35.873,
      "end": 35.954,
      "duration": 0.08100000000000307
    },
    {
      "word": "threaten",
      "start": 36.055,
      "end": 36.421,
      "duration": 0.36599999999999966
    },
    {
      "word": "us",
      "start": 36.481,
      "end": 36.542,
      "duration": 0.06099999999999994
    },
    {
      "word": "multiple",
      "start": 36.725,
      "end": 37.211,
      "duration": 0.4859999999999971
    },
    {
      "word": "times.",
      "start": 37.252,
      "end": 37.779,
      "duration": 0.527000000000001
    },
    {
      "word": "When",
      "start": 37.759,
      "end": 38.197,
      "duration": 0.4380000000000024
    },
    {
      "word": "he...",
      "start": 38.217,
      "end": 38.78,
      "duration": 0.5630000000000024
    },
    {
      "word": "Straight",
      "start": 38.759,
      "end": 39.639,
      "duration": 0.8800000000000026
    },
    {
      "word": "up",
      "start": 39.72,
      "end": 39.802,
      "duration": 0.08200000000000074
    },
    {
      "word": "demanding...",
      "start": 39.843,
      "end": 40.58,
      "duration": 0.7369999999999948
    },
    {
      "word": "That",
      "start": 40.559,
      "end": 41.903,
      "duration": 1.3440000000000012
    },
    {
      "word": "we",
      "start": 41.944,
      "end": 42.086,
      "duration": 0.1419999999999959
    },
    {
      "word": "do",
      "start": 42.147,
      "end": 42.29,
      "duration": 0.14300000000000068
    },
    {
      "word": "this.",
      "start": 42.351,
      "end": 42.819,
      "duration": 0.4680000000000035
    },
    {
      "word": "Demanding",
      "start": 42.799,
      "end": 43.424,
      "duration": 0.625
    },
    {
      "word": "it.",
      "start": 43.487,
      "end": 43.82,
      "duration": 0.3329999999999984
    },
    {
      "word": "Demanding",
      "start": 43.799,
      "end": 44.362,
      "duration": 0.5630000000000024
    },
    {
      "word": "it.",
      "start": 44.757,
      "end": 44.82,
      "duration": 0.06300000000000239
    },
    {
      "word": "Dude,",
      "start": 44.799,
      "end": 45.085,
      "duration": 0.28600000000000136
    },
    {
      "word": "who",
      "start": 45.146,
      "end": 45.268,
      "duration": 0.12199999999999989
    },
    {
      "word": "do",
      "start": 45.575,
      "end": 45.615,
      "duration": 0.03999999999999915
    },
    {
      "word": "you",
      "start": 45.636,
      "end": 45.697,
      "duration": 0.06099999999999994
    },
    {
      "word": "think",
      "start": 45.799,
      "end": 46.105,
      "duration": 0.3059999999999974
    },
    {
      "word": "you",
      "start": 46.126,
      "end": 46.187,
      "duration": 0.06099999999999994
    },
    {
      "word": "are,",
      "start": 46.207,
      "end": 46.575,
      "duration": 0.3680000000000021
    },
    {
      "word": "little",
      "start": 46.595,
      "end": 46.717,
      "duration": 0.12199999999999989
    },
    {
      "word": "man?",
      "start": 46.738,
      "end": 46.82,
      "duration": 0.08200000000000074
    },
    {
      "word": "You",
      "start": 46.799,
      "end": 48.201,
      "duration": 1.402000000000001
    },
    {
      "word": "know",
      "start": 48.242,
      "end": 48.323,
      "duration": 0.08100000000000307
    },
    {
      "word": "what",
      "start": 48.343,
      "end": 48.424,
      "duration": 0.08099999999999596
    },
    {
      "word": "I'm",
      "start": 48.506,
      "end": 48.567,
      "duration": 0.06099999999999994
    },
    {
      "word": "saying?",
      "start": 49.237,
      "end": 49.379,
      "duration": 0.1419999999999959
    },
    {
      "word": "Like,",
      "start": 49.359,
      "end": 49.502,
      "duration": 0.14300000000000068
    },
    {
      "word": "bro,",
      "start": 49.523,
      "end": 49.707,
      "duration": 0.1839999999999975
    },
    {
      "word": "I",
      "start": 49.768,
      "end": 49.891,
      "duration": 0.12299999999999756
    },
    {
      "word": "beat",
      "start": 49.932,
      "end": 50.136,
      "duration": 0.20400000000000063
    },
    {
      "word": "your",
      "start": 50.177,
      "end": 50.32,
      "duration": 0.14300000000000068
    },
    {
      "word": "fucking",
      "start": 50.361,
      "end": 50.689,
      "duration": 0.32800000000000296
    },
    {
      "word": "ass.",
      "start": 50.832,
      "end": 51.18,
      "duration": 0.347999999999999
    },
    {
      "word": "So",
      "start": 52.327,
      "end": 52.569,
      "duration": 0.24200000000000443
    },
    {
      "word": "fucking,",
      "start": 52.873,
      "end": 53.176,
      "duration": 0.3030000000000044
    },
    {
      "word": "oh",
      "start": 53.217,
      "end": 53.318,
      "duration": 0.10099999999999909
    },
    {
      "word": "just",
      "start": 53.358,
      "end": 53.5,
      "duration": 0.142000000000003
    },
    {
      "word": "about,",
      "start": 53.561,
      "end": 53.723,
      "duration": 0.16199999999999903
    },
    {
      "word": "the",
      "start": 53.743,
      "end": 54.228,
      "duration": 0.48499999999999943
    },
    {
      "word": "guy's",
      "start": 54.269,
      "end": 54.512,
      "duration": 0.2430000000000021
    },
    {
      "word": "fucking",
      "start": 54.613,
      "end": 54.937,
      "duration": 0.32399999999999807
    },
    {
      "word": "five,",
      "start": 55.018,
      "end": 55.301,
      "duration": 0.28300000000000125
    },
    {
      "word": "five.",
      "start": 55.341,
      "end": 55.827,
      "duration": 0.4859999999999971
    },
    {
      "word": "Five",
      "start": 55.807,
      "end": 56.437,
      "duration": 0.6299999999999955
    },
    {
      "word": "eight.",
      "start": 56.458,
      "end": 56.668,
      "duration": 0.21000000000000085
    },
    {
      "word": "He's",
      "start": 56.647,
      "end": 56.832,
      "duration": 0.18500000000000227
    },
    {
      "word": "over,",
      "start": 56.894,
      "end": 57.203,
      "duration": 0.3090000000000046
    },
    {
      "word": "no,",
      "start": 57.265,
      "end": 57.388,
      "duration": 0.12299999999999756
    },
    {
      "word": "he",
      "start": 57.409,
      "end": 57.491,
      "duration": 0.08200000000000074
    },
    {
      "word": "ain't.",
      "start": 57.553,
      "end": 58.027,
      "duration": 0.47400000000000375
    },
    {
      "word": "If",
      "start": 58.007,
      "end": 58.088,
      "duration": 0.08100000000000307
    },
    {
      "word": "they",
      "start": 58.129,
      "end": 58.272,
      "duration": 0.14300000000000068
    },
    {
      "word": "claim",
      "start": 58.333,
      "end": 58.681,
      "duration": 0.347999999999999
    },
    {
      "word": "five",
      "start": 58.701,
      "end": 58.946,
      "duration": 0.24499999999999744
    },
    {
      "word": "eight,",
      "start": 59.007,
      "end": 59.13,
      "duration": 0.12300000000000466
    },
    {
      "word": "he's",
      "start": 59.15,
      "end": 59.273,
      "duration": 0.12300000000000466
    },
    {
      "word": "five",
      "start": 59.314,
      "end": 59.518,
      "duration": 0.20400000000000063
    },
    {
      "word": "five.",
      "start": 59.539,
      "end": 59.947,
      "duration": 0.40800000000000125
    },
    {
      "word": "That's",
      "start": 59.927,
      "end": 60.255,
      "duration": 0.32800000000000296
    },
    {
      "word": "not",
      "start": 60.275,
      "end": 60.378,
      "duration": 0.10300000000000153
    },
    {
      "word": "the",
      "start": 60.398,
      "end": 60.48,
      "duration": 0.08199999999999363
    },
    {
      "word": "internet",
      "start": 60.521,
      "end": 60.808,
      "duration": 0.28699999999999903
    },
    {
      "word": "works.",
      "start": 60.87,
      "end": 61.587,
      "duration": 0.7170000000000059
    },
    {
      "word": "Okay.",
      "start": 61.567,
      "end": 62.747,
      "duration": 1.1799999999999997
    },
    {
      "word": "So,",
      "start": 62.727,
      "end": 63.093,
      "duration": 0.36600000000000676
    },
    {
      "word": "let's",
      "start": 63.155,
      "end": 64.581,
      "duration": 1.426000000000002
    },
    {
      "word": "true.",
      "start": 64.622,
      "end": 64.907,
      "duration": 0.2849999999999966
    },
    {
      "word": "Let's",
      "start": 64.887,
      "end": 65.118,
      "duration": 0.23099999999999454
    },
    {
      "word": "true.",
      "start": 65.139,
      "end": 65.748,
      "duration": 0.6090000000000089
    },
    {
      "word": "Yeah.",
      "start": 65.727,
      "end": 66.747,
      "duration": 1.019999999999996
    },
    {
      "word": "So,",
      "start": 66.727,
      "end": 66.975,
      "duration": 0.24799999999999045
    },
    {
      "word": "you",
      "start": 67.244,
      "end": 67.347,
      "duration": 0.10299999999999443
    },
    {
      "word": "know,",
      "start": 67.368,
      "end": 67.947,
      "duration": 0.5790000000000077
    },
    {
      "word": "I",
      "start": 70.147,
      "end": 70.449,
      "duration": 0.3019999999999925
    },
    {
      "word": "don't",
      "start": 70.53,
      "end": 70.692,
      "duration": 0.16199999999999193
    },
    {
      "word": "know",
      "start": 71.014,
      "end": 71.156,
      "duration": 0.14200000000001012
    },
    {
      "word": "dude.",
      "start": 71.176,
      "end": 71.358,
      "duration": 0.18200000000000216
    },
    {
      "word": "I",
      "start": 71.519,
      "end": 71.58,
      "duration": 0.06099999999999284
    },
    {
      "word": "don't",
      "start": 71.6,
      "end": 71.761,
      "duration": 0.16100000000000136
    },
    {
      "word": "think",
      "start": 71.802,
      "end": 71.923,
      "duration": 0.12099999999999511
    },
    {
      "word": "shit's",
      "start": 71.983,
      "end": 72.246,
      "duration": 0.262999999999991
    },
    {
      "word": "big",
      "start": 72.266,
      "end": 72.448,
      "duration": 0.18199999999998795
    },
    {
      "word": "and",
      "start": 72.468,
      "end": 72.589,
      "duration": 0.12099999999999511
    },
    {
      "word": "did",
      "start": 72.629,
      "end": 72.69,
      "duration": 0.06099999999999284
    },
    {
      "word": "you",
      "start": 72.71,
      "end": 72.791,
      "duration": 0.08100000000000307
    },
    {
      "word": "see",
      "start": 72.831,
      "end": 72.952,
      "duration": 0.12099999999999511
    },
    {
      "word": "that",
      "start": 72.972,
      "end": 73.114,
      "duration": 0.14200000000001012
    },
    {
      "word": "fucking",
      "start": 73.174,
      "end": 73.437,
      "duration": 0.262999999999991
    },
    {
      "word": "video",
      "start": 73.457,
      "end": 73.82,
      "duration": 0.36299999999999955
    },
    {
      "word": "that",
      "start": 73.86,
      "end": 73.961,
      "duration": 0.10099999999999909
    },
    {
      "word": "do",
      "start": 74.103,
      "end": 74.284,
      "duration": 0.1810000000000116
    },
    {
      "word": "crying?",
      "start": 74.425,
      "end": 74.567,
      "duration": 0.1419999999999959
    },
    {
      "word": "The",
      "start": 75.107,
      "end": 75.73,
      "duration": 0.6230000000000047
    },
    {
      "word": "back.",
      "start": 76.616,
      "end": 76.898,
      "duration": 0.2819999999999965
    },
    {
      "word": "Oh",
      "start": 77.159,
      "end": 77.34,
      "duration": 0.18099999999999739
    },
    {
      "word": "dude",
      "start": 77.441,
      "end": 77.703,
      "duration": 0.26200000000000045
    },
    {
      "word": "dude.",
      "start": 78.085,
      "end": 78.326,
      "duration": 0.24099999999999966
    },
    {
      "word": "I",
      "start": 78.588,
      "end": 78.648,
      "duration": 0.060000000000002274
    },
    {
      "word": "thought",
      "start": 78.689,
      "end": 78.87,
      "duration": 0.1810000000000116
    },
    {
      "word": "that",
      "start": 78.89,
      "end": 79.011,
      "duration": 0.12099999999999511
    },
    {
      "word": "was",
      "start": 79.091,
      "end": 79.172,
      "duration": 0.08100000000000307
    },
    {
      "word": "like",
      "start": 79.232,
      "end": 79.373,
      "duration": 0.14100000000000534
    },
    {
      "word": "a",
      "start": 79.393,
      "end": 79.413,
      "duration": 0.01999999999999602
    },
    {
      "word": "fake.",
      "start": 79.715,
      "end": 79.957,
      "duration": 0.24199999999999022
    },
    {
      "word": "I",
      "start": 80.077,
      "end": 80.118,
      "duration": 0.04099999999999682
    },
    {
      "word": "thought",
      "start": 80.178,
      "end": 80.359,
      "duration": 0.18099999999999739
    },
    {
      "word": "it",
      "start": 80.419,
      "end": 80.46,
      "duration": 0.04099999999999682
    },
    {
      "word": "was",
      "start": 80.5,
      "end": 80.681,
      "duration": 0.18099999999999739
    },
    {
      "word": "a",
      "start": 80.762,
      "end": 80.822,
      "duration": 0.060000000000002274
    },
    {
      "word": "first",
      "start": 80.862,
      "end": 81.124,
      "duration": 0.26200000000000045
    },
    {
      "word": "time",
      "start": 81.164,
      "end": 81.446,
      "duration": 0.2819999999999965
    },
    {
      "word": "dude",
      "start": 81.486,
      "end": 81.607,
      "duration": 0.12099999999999511
    },
    {
      "word": "You",
      "start": 81.587,
      "end": 81.808,
      "duration": 0.22100000000000364
    },
    {
      "word": "know",
      "start": 81.849,
      "end": 81.97,
      "duration": 0.12099999999999511
    },
    {
      "word": "what",
      "start": 81.99,
      "end": 82.071,
      "duration": 0.08100000000000307
    },
    {
      "word": "that",
      "start": 82.111,
      "end": 82.232,
      "duration": 0.12099999999999511
    },
    {
      "word": "guy",
      "start": 82.454,
      "end": 82.595,
      "duration": 0.14100000000000534
    },
    {
      "word": "has",
      "start": 82.635,
      "end": 82.777,
      "duration": 0.1419999999999959
    },
    {
      "word": "to",
      "start": 82.817,
      "end": 82.877,
      "duration": 0.060000000000002274
    },
    {
      "word": "be",
      "start": 82.918,
      "end": 82.998,
      "duration": 0.0799999999999983
    },
    {
      "word": "a",
      "start": 83.039,
      "end": 83.059,
      "duration": 0.01999999999999602
    },
    {
      "word": "fucking",
      "start": 83.14,
      "end": 83.462,
      "duration": 0.32200000000000273
    },
    {
      "word": "influencer",
      "start": 83.482,
      "end": 84.168,
      "duration": 0.686000000000007
    },
    {
      "word": "that",
      "start": 84.229,
      "end": 84.329,
      "duration": 0.09999999999999432
    },
    {
      "word": "they",
      "start": 84.35,
      "end": 84.491,
      "duration": 0.14100000000000534
    },
    {
      "word": "paid",
      "start": 84.531,
      "end": 84.713,
      "duration": 0.18199999999998795
    },
    {
      "word": "to",
      "start": 84.733,
      "end": 84.813,
      "duration": 0.0799999999999983
    },
    {
      "word": "do",
      "start": 84.834,
      "end": 84.934,
      "duration": 0.09999999999999432
    },
    {
      "word": "that.",
      "start": 84.975,
      "end": 85.116,
      "duration": 0.14100000000000534
    },
    {
      "word": "Yeah,",
      "start": 85.136,
      "end": 85.459,
      "duration": 0.3230000000000075
    },
    {
      "word": "there's",
      "start": 85.499,
      "end": 85.701,
      "duration": 0.20199999999999818
    },
    {
      "word": "no",
      "start": 85.761,
      "end": 85.862,
      "duration": 0.10099999999999909
    },
    {
      "word": "fucking",
      "start": 85.963,
      "end": 86.306,
      "duration": 0.3430000000000035
    },
    {
      "word": "way",
      "start": 86.346,
      "end": 86.407,
      "duration": 0.06099999999999284
    },
    {
      "word": "I'm",
      "start": 87.427,
      "end": 87.853,
      "duration": 0.4259999999999877
    },
    {
      "word": "not",
      "start": 87.894,
      "end": 87.995,
      "duration": 0.10099999999999909
    },
    {
      "word": "crying",
      "start": 88.056,
      "end": 88.422,
      "duration": 0.36599999999999966
    },
    {
      "word": "on",
      "start": 88.442,
      "end": 88.483,
      "duration": 0.04100000000001103
    },
    {
      "word": "TV.",
      "start": 88.523,
      "end": 88.848,
      "duration": 0.32500000000000284
    },
    {
      "word": "I'm",
      "start": 89.539,
      "end": 89.66,
      "duration": 0.12099999999999511
    },
    {
      "word": "not",
      "start": 89.681,
      "end": 89.803,
      "duration": 0.12199999999999989
    },
    {
      "word": "crying",
      "start": 89.843,
      "end": 90.087,
      "duration": 0.24399999999999977
    }
  ],
  "lightning_words": [
    {
      "word": "that's",
      "start": 0.0,
      "end": 1.162,
      "duration": 1.162
    },
    {
      "word": "why",
      "start": 1.182,
      "end": 1.302,
      "duration": 0.1200000000000001
    },
    {
      "word": "he's",
      "start": 1.342,
      "end": 1.442,
      "duration": 0.09999999999999987
    },
    {
      "word": "so",
      "start": 1.462,
      "end": 1.602,
      "duration": 0.14000000000000012
    },
    {
      "word": "fucking",
      "start": 1.642,
      "end": 1.923,
      "duration": 0.28100000000000014
    },
    {
      "word": "famous",
      "start": 1.963,
      "end": 2.263,
      "duration": 0.2999999999999998
    },
    {
      "word": "bro",
      "start": 2.283,
      "end": 2.543,
      "duration": 0.26000000000000023
    },
    {
      "word": "that's",
      "start": 3.665,
      "end": 3.825,
      "duration": 0.16000000000000014
    },
    {
      "word": "why",
      "start": 3.865,
      "end": 3.945,
      "duration": 0.07999999999999963
    },
    {
      "word": "Gordon",
      "start": 4.045,
      "end": 4.246,
      "duration": 0.2010000000000005
    },
    {
      "word": "Ramsay's",
      "start": 4.266,
      "end": 4.606,
      "duration": 0.33999999999999986
    },
    {
      "word": "so",
      "start": 4.626,
      "end": 4.766,
      "duration": 0.13999999999999968
    },
    {
      "word": "famous",
      "start": 4.826,
      "end": 5.267,
      "duration": 0.4410000000000007
    },
    {
      "word": "because",
      "start": 5.307,
      "end": 5.487,
      "duration": 0.17999999999999972
    },
    {
      "word": "he's",
      "start": 5.507,
      "end": 5.628,
      "duration": 0.12100000000000044
    },
    {
      "word": "only",
      "start": 5.668,
      "end": 5.908,
      "duration": 0.2400000000000002
    },
    {
      "word": "one",
      "start": 5.968,
      "end": 6.088,
      "duration": 0.1200000000000001
    },
    {
      "word": "over",
      "start": 6.128,
      "end": 6.268,
      "duration": 0.13999999999999968
    },
    {
      "word": "there",
      "start": 6.308,
      "end": 6.429,
      "duration": 0.12100000000000044
    },
    {
      "word": "who",
      "start": 6.449,
      "end": 6.509,
      "duration": 0.0600000000000005
    },
    {
      "word": "knows",
      "start": 6.529,
      "end": 6.649,
      "duration": 0.1200000000000001
    },
    {
      "word": "how",
      "start": 6.689,
      "end": 6.749,
      "duration": 0.05999999999999961
    },
    {
      "word": "to",
      "start": 6.769,
      "end": 6.809,
      "duration": 0.040000000000000036
    },
    {
      "word": "make",
      "start": 6.829,
      "end": 6.989,
      "duration": 0.16000000000000014
    },
    {
      "word": "food",
      "start": 7.029,
      "end": 7.25,
      "duration": 0.22100000000000009
    },
    {
      "word": "he",
      "start": 7.29,
      "end": 7.33,
      "duration": 0.040000000000000036
    },
    {
      "word": "goes",
      "start": 10.915,
      "end": 13.418,
      "duration": 2.503
    },
    {
      "word": "to",
      "start": 13.458,
      "end": 13.598,
      "duration": 0.14000000000000057
    },
    {
      "word": "UK",
      "start": 13.718,
      "end": 14.039,
      "duration": 0.32099999999999973
    },
    {
      "word": "he",
      "start": 14.059,
      "end": 14.099,
      "duration": 0.040000000000000924
    },
    {
      "word": "goes",
      "start": 14.119,
      "end": 14.299,
      "duration": 0.17999999999999972
    },
    {
      "word": "with",
      "start": 14.359,
      "end": 14.439,
      "duration": 0.08000000000000007
    },
    {
      "word": "UK",
      "start": 14.559,
      "end": 14.92,
      "duration": 0.36100000000000065
    },
    {
      "word": "he",
      "start": 15.421,
      "end": 15.501,
      "duration": 0.08000000000000007
    },
    {
      "word": "meets",
      "start": 15.541,
      "end": 15.821,
      "duration": 0.27999999999999936
    },
    {
      "word": "with",
      "start": 16.482,
      "end": 16.782,
      "duration": 0.3000000000000007
    },
    {
      "word": "King",
      "start": 17.063,
      "end": 17.243,
      "duration": 0.17999999999999972
    },
    {
      "word": "Charles",
      "start": 17.343,
      "end": 17.964,
      "duration": 0.6209999999999987
    },
    {
      "word": "I",
      "start": 18.124,
      "end": 18.184,
      "duration": 0.060000000000002274
    },
    {
      "word": "mean",
      "start": 18.204,
      "end": 18.324,
      "duration": 0.120000000000001
    },
    {
      "word": "this",
      "start": 18.344,
      "end": 18.445,
      "duration": 0.10099999999999909
    },
    {
      "word": "is",
      "start": 18.505,
      "end": 18.545,
      "duration": 0.0400000000000027
    },
    {
      "word": "right",
      "start": 18.605,
      "end": 18.745,
      "duration": 0.14000000000000057
    },
    {
      "word": "after",
      "start": 18.785,
      "end": 19.005,
      "duration": 0.21999999999999886
    },
    {
      "word": "he",
      "start": 19.586,
      "end": 19.646,
      "duration": 0.060000000000002274
    },
    {
      "word": "got",
      "start": 19.686,
      "end": 19.846,
      "duration": 0.16000000000000014
    },
    {
      "word": "kicked",
      "start": 19.907,
      "end": 20.107,
      "duration": 0.1999999999999993
    },
    {
      "word": "out",
      "start": 20.167,
      "end": 20.227,
      "duration": 0.05999999999999872
    },
    {
      "word": "the",
      "start": 20.267,
      "end": 20.347,
      "duration": 0.08000000000000185
    },
    {
      "word": "White",
      "start": 20.407,
      "end": 20.547,
      "duration": 0.14000000000000057
    },
    {
      "word": "House",
      "start": 20.587,
      "end": 20.768,
      "duration": 0.18100000000000094
    },
    {
      "word": "I",
      "start": 20.888,
      "end": 20.908,
      "duration": 0.019999999999999574
    },
    {
      "word": "don't",
      "start": 20.948,
      "end": 21.068,
      "duration": 0.120000000000001
    },
    {
      "word": "know",
      "start": 21.088,
      "end": 21.188,
      "duration": 0.09999999999999787
    },
    {
      "word": "if",
      "start": 21.228,
      "end": 21.268,
      "duration": 0.03999999999999915
    },
    {
      "word": "I've",
      "start": 21.869,
      "end": 22.029,
      "duration": 0.16000000000000014
    },
    {
      "word": "had",
      "start": 22.049,
      "end": 22.19,
      "duration": 0.1410000000000018
    },
    {
      "word": "to",
      "start": 22.21,
      "end": 22.31,
      "duration": 0.09999999999999787
    },
    {
      "word": "verify",
      "start": 22.35,
      "end": 22.891,
      "duration": 0.5409999999999968
    },
    {
      "word": "that",
      "start": 22.931,
      "end": 23.111,
      "duration": 0.17999999999999972
    },
    {
      "word": "he",
      "start": 23.151,
      "end": 23.832,
      "duration": 0.6810000000000009
    },
    {
      "word": "was",
      "start": 23.872,
      "end": 23.972,
      "duration": 0.10000000000000142
    },
    {
      "word": "kicked",
      "start": 24.032,
      "end": 24.212,
      "duration": 0.17999999999999972
    },
    {
      "word": "out",
      "start": 24.272,
      "end": 24.352,
      "duration": 0.08000000000000185
    },
    {
      "word": "the",
      "start": 24.393,
      "end": 24.493,
      "duration": 0.09999999999999787
    },
    {
      "word": "fucking",
      "start": 24.533,
      "end": 24.773,
      "duration": 0.23999999999999844
    },
    {
      "word": "White",
      "start": 24.793,
      "end": 24.953,
      "duration": 0.16000000000000014
    },
    {
      "word": "House",
      "start": 24.973,
      "end": 25.174,
      "duration": 0.2010000000000005
    },
    {
      "word": "after",
      "start": 25.614,
      "end": 25.774,
      "duration": 0.16000000000000014
    },
    {
      "word": "that",
      "start": 25.794,
      "end": 25.935,
      "duration": 0.14099999999999824
    },
    {
      "word": "fucking",
      "start": 25.975,
      "end": 26.435,
      "duration": 0.4599999999999973
    },
    {
      "word": "meeting",
      "start": 26.475,
      "end": 30.02,
      "duration": 3.544999999999998
    },
    {
      "word": "Half",
      "start": 30.0,
      "end": 30.32,
      "duration": 0.3200000000000003
    },
    {
      "word": "a",
      "start": 30.441,
      "end": 30.541,
      "duration": 0.10000000000000142
    },
    {
      "word": "pound",
      "start": 30.661,
      "end": 30.941,
      "duration": 0.2799999999999976
    },
    {
      "word": "of",
      "start": 30.961,
      "end": 31.001,
      "duration": 0.0400000000000027
    },
    {
      "word": "that",
      "start": 31.021,
      "end": 31.101,
      "duration": 0.0799999999999983
    },
    {
      "word": "listen",
      "start": 31.162,
      "end": 31.442,
      "duration": 0.28000000000000114
    },
    {
      "word": "and",
      "start": 31.562,
      "end": 31.642,
      "duration": 0.0799999999999983
    },
    {
      "word": "dude",
      "start": 31.662,
      "end": 31.842,
      "duration": 0.17999999999999972
    },
    {
      "word": "real",
      "start": 31.903,
      "end": 32.083,
      "duration": 0.17999999999999972
    },
    {
      "word": "talk",
      "start": 32.123,
      "end": 32.363,
      "duration": 0.240000000000002
    },
    {
      "word": "the",
      "start": 32.664,
      "end": 32.764,
      "duration": 0.10000000000000142
    },
    {
      "word": "motherfucker",
      "start": 32.784,
      "end": 33.284,
      "duration": 0.5
    },
    {
      "word": "has",
      "start": 33.324,
      "end": 33.405,
      "duration": 0.08100000000000307
    },
    {
      "word": "never",
      "start": 33.445,
      "end": 33.665,
      "duration": 0.21999999999999886
    },
    {
      "word": "said",
      "start": 33.725,
      "end": 33.885,
      "duration": 0.1599999999999966
    },
    {
      "word": "thank",
      "start": 33.945,
      "end": 34.126,
      "duration": 0.18099999999999739
    },
    {
      "word": "you",
      "start": 34.166,
      "end": 34.306,
      "duration": 0.14000000000000057
    },
    {
      "word": "ever",
      "start": 34.546,
      "end": 34.746,
      "duration": 0.20000000000000284
    },
    {
      "word": "He's",
      "start": 35.007,
      "end": 35.207,
      "duration": 0.20000000000000284
    },
    {
      "word": "come",
      "start": 35.327,
      "end": 35.587,
      "duration": 0.2600000000000051
    },
    {
      "word": "here",
      "start": 35.648,
      "end": 35.808,
      "duration": 0.1599999999999966
    },
    {
      "word": "and",
      "start": 35.868,
      "end": 35.948,
      "duration": 0.0799999999999983
    },
    {
      "word": "threaten",
      "start": 36.048,
      "end": 36.409,
      "duration": 0.3609999999999971
    },
    {
      "word": "us",
      "start": 36.469,
      "end": 36.529,
      "duration": 0.060000000000002274
    },
    {
      "word": "multiple",
      "start": 36.729,
      "end": 37.25,
      "duration": 0.5210000000000008
    },
    {
      "word": "times",
      "start": 37.45,
      "end": 37.65,
      "duration": 0.19999999999999574
    },
    {
      "word": "it",
      "start": 37.73,
      "end": 37.83,
      "duration": 0.10000000000000142
    },
    {
      "word": "when",
      "start": 38.051,
      "end": 38.171,
      "duration": 0.11999999999999744
    },
    {
      "word": "he",
      "start": 38.211,
      "end": 38.351,
      "duration": 0.14000000000000057
    },
    {
      "word": "dude",
      "start": 38.531,
      "end": 38.812,
      "duration": 0.2809999999999988
    },
    {
      "word": "straight",
      "start": 39.252,
      "end": 39.633,
      "duration": 0.3810000000000002
    },
    {
      "word": "up",
      "start": 39.713,
      "end": 39.793,
      "duration": 0.0799999999999983
    },
    {
      "word": "demanding",
      "start": 39.833,
      "end": 40.594,
      "duration": 0.7610000000000028
    },
    {
      "word": "That",
      "start": 40.634,
      "end": 41.896,
      "duration": 1.2620000000000005
    },
    {
      "word": "we",
      "start": 41.936,
      "end": 42.096,
      "duration": 0.1599999999999966
    },
    {
      "word": "do",
      "start": 42.136,
      "end": 42.276,
      "duration": 0.14000000000000057
    },
    {
      "word": "this",
      "start": 42.336,
      "end": 42.517,
      "duration": 0.1810000000000045
    },
    {
      "word": "demanding",
      "start": 42.897,
      "end": 44.019,
      "duration": 1.1219999999999999
    },
    {
      "word": "it.",
      "start": 44.079,
      "end": 44.139,
      "duration": 0.060000000000002274
    },
    {
      "word": "Do",
      "start": 44.199,
      "end": 44.339,
      "duration": 0.14000000000000057
    },
    {
      "word": "who",
      "start": 44.419,
      "end": 44.559,
      "duration": 0.14000000000000057
    },
    {
      "word": "do",
      "start": 44.579,
      "end": 44.619,
      "duration": 0.03999999999999915
    },
    {
      "word": "you",
      "start": 44.68,
      "end": 44.82,
      "duration": 0.14000000000000057
    },
    {
      "word": "think",
      "start": 44.9,
      "end": 45.1,
      "duration": 0.20000000000000284
    },
    {
      "word": "you",
      "start": 45.14,
      "end": 45.26,
      "duration": 0.11999999999999744
    },
    {
      "word": "are",
      "start": 45.501,
      "end": 45.601,
      "duration": 0.10000000000000142
    },
    {
      "word": "little",
      "start": 45.741,
      "end": 45.921,
      "duration": 0.17999999999999972
    },
    {
      "word": "man?",
      "start": 45.961,
      "end": 46.202,
      "duration": 0.24099999999999966
    },
    {
      "word": "You",
      "start": 47.944,
      "end": 48.004,
      "duration": 0.05999999999999517
    },
    {
      "word": "know",
      "start": 48.104,
      "end": 48.204,
      "duration": 0.10000000000000142
    },
    {
      "word": "what",
      "start": 48.264,
      "end": 48.344,
      "duration": 0.0799999999999983
    },
    {
      "word": "I'm",
      "start": 48.364,
      "end": 48.425,
      "duration": 0.06099999999999994
    },
    {
      "word": "saying",
      "start": 48.445,
      "end": 48.585,
      "duration": 0.14000000000000057
    },
    {
      "word": "like",
      "start": 49.386,
      "end": 49.506,
      "duration": 0.11999999999999744
    },
    {
      "word": "bro,",
      "start": 49.546,
      "end": 49.726,
      "duration": 0.17999999999999972
    },
    {
      "word": "I'll",
      "start": 49.806,
      "end": 49.907,
      "duration": 0.10099999999999909
    },
    {
      "word": "beat",
      "start": 49.967,
      "end": 50.167,
      "duration": 0.20000000000000284
    },
    {
      "word": "your",
      "start": 50.187,
      "end": 50.327,
      "duration": 0.14000000000000057
    },
    {
      "word": "fucking",
      "start": 50.367,
      "end": 50.688,
      "duration": 0.32100000000000506
    },
    {
      "word": "ass",
      "start": 50.828,
      "end": 51.008,
      "duration": 0.17999999999999972
    },
    {
      "word": "So",
      "start": 52.43,
      "end": 52.59,
      "duration": 0.1600000000000037
    },
    {
      "word": "what",
      "start": 52.71,
      "end": 52.79,
      "duration": 0.0799999999999983
    },
    {
      "word": "fucking",
      "start": 52.891,
      "end": 53.171,
      "duration": 0.28000000000000114
    },
    {
      "word": "oh",
      "start": 53.231,
      "end": 53.351,
      "duration": 0.11999999999999744
    },
    {
      "word": "just",
      "start": 53.371,
      "end": 53.531,
      "duration": 0.1599999999999966
    },
    {
      "word": "about",
      "start": 53.571,
      "end": 53.732,
      "duration": 0.16100000000000136
    },
    {
      "word": "they",
      "start": 53.752,
      "end": 54.252,
      "duration": 0.5
    },
    {
      "word": "guys",
      "start": 54.272,
      "end": 54.513,
      "duration": 0.24099999999999966
    },
    {
      "word": "fucking",
      "start": 54.613,
      "end": 54.933,
      "duration": 0.3200000000000003
    },
    {
      "word": "five",
      "start": 55.013,
      "end": 55.274,
      "duration": 0.2610000000000028
    },
    {
      "word": "five",
      "start": 55.334,
      "end": 55.674,
      "duration": 0.3399999999999963
    },
    {
      "word": "five",
      "start": 56.155,
      "end": 56.455,
      "duration": 0.29999999999999716
    },
    {
      "word": "eight",
      "start": 56.475,
      "end": 56.615,
      "duration": 0.14000000000000057
    },
    {
      "word": "he's",
      "start": 56.716,
      "end": 56.856,
      "duration": 0.14000000000000057
    },
    {
      "word": "over",
      "start": 56.916,
      "end": 57.076,
      "duration": 0.1600000000000037
    },
    {
      "word": "here.",
      "start": 57.176,
      "end": 57.276,
      "duration": 0.10000000000000142
    },
    {
      "word": "No,",
      "start": 57.296,
      "end": 57.417,
      "duration": 0.12100000000000222
    },
    {
      "word": "he",
      "start": 57.437,
      "end": 57.497,
      "duration": 0.060000000000002274
    },
    {
      "word": "ain't",
      "start": 57.557,
      "end": 57.697,
      "duration": 0.14000000000000057
    },
    {
      "word": "if",
      "start": 58.077,
      "end": 58.138,
      "duration": 0.06099999999999994
    },
    {
      "word": "they",
      "start": 58.178,
      "end": 58.298,
      "duration": 0.12000000000000455
    },
    {
      "word": "claim",
      "start": 58.378,
      "end": 58.638,
      "duration": 0.259999999999998
    },
    {
      "word": "five",
      "start": 58.718,
      "end": 58.959,
      "duration": 0.24099999999999966
    },
    {
      "word": "eight",
      "start": 59.019,
      "end": 60.02,
      "duration": 1.0010000000000048
    },
    {
      "word": "You",
      "start": 60.0,
      "end": 60.18,
      "duration": 0.17999999999999972
    },
    {
      "word": "know",
      "start": 60.2,
      "end": 60.28,
      "duration": 0.0799999999999983
    },
    {
      "word": "how",
      "start": 60.3,
      "end": 60.36,
      "duration": 0.060000000000002274
    },
    {
      "word": "the",
      "start": 60.401,
      "end": 60.461,
      "duration": 0.05999999999999517
    },
    {
      "word": "internet",
      "start": 60.501,
      "end": 60.781,
      "duration": 0.28000000000000114
    },
    {
      "word": "works.",
      "start": 60.821,
      "end": 61.041,
      "duration": 0.21999999999999886
    },
    {
      "word": "Okay,",
      "start": 61.822,
      "end": 62.864,
      "duration": 1.0419999999999945
    },
    {
      "word": "so",
      "start": 62.884,
      "end": 63.124,
      "duration": 0.240000000000002
    },
    {
      "word": "It's",
      "start": 64.446,
      "end": 64.546,
      "duration": 0.10000000000000853
    },
    {
      "word": "true.",
      "start": 64.586,
      "end": 64.866,
      "duration": 0.28000000000000114
    },
    {
      "word": "That's",
      "start": 64.967,
      "end": 65.107,
      "duration": 0.14000000000000057
    },
    {
      "word": "true.",
      "start": 65.147,
      "end": 65.307,
      "duration": 0.1599999999999966
    },
    {
      "word": "Yeah,",
      "start": 65.668,
      "end": 65.788,
      "duration": 0.11999999999999034
    },
    {
      "word": "it's",
      "start": 65.808,
      "end": 65.888,
      "duration": 0.0799999999999983
    },
    {
      "word": "five",
      "start": 65.968,
      "end": 66.108,
      "duration": 0.14000000000000057
    },
    {
      "word": "five",
      "start": 66.128,
      "end": 66.348,
      "duration": 0.21999999999999886
    },
    {
      "word": "so",
      "start": 66.749,
      "end": 66.969,
      "duration": 0.21999999999999886
    },
    {
      "word": "you",
      "start": 67.25,
      "end": 67.33,
      "duration": 0.0799999999999983
    },
    {
      "word": "know",
      "start": 67.37,
      "end": 67.55,
      "duration": 0.1799999999999926
    },
    {
      "word": "I",
      "start": 67.57,
      "end": 67.59,
      "duration": 0.020000000000010232
    },
    {
      "word": "don't",
      "start": 70.534,
      "end": 70.714,
      "duration": 0.1799999999999926
    },
    {
      "word": "I",
      "start": 70.774,
      "end": 70.814,
      "duration": 0.03999999999999204
    },
    {
      "word": "don't",
      "start": 70.874,
      "end": 70.995,
      "duration": 0.12100000000000932
    },
    {
      "word": "know",
      "start": 71.015,
      "end": 71.155,
      "duration": 0.14000000000000057
    },
    {
      "word": "dude.",
      "start": 71.175,
      "end": 71.375,
      "duration": 0.20000000000000284
    },
    {
      "word": "I",
      "start": 71.515,
      "end": 71.575,
      "duration": 0.060000000000002274
    },
    {
      "word": "don't",
      "start": 71.615,
      "end": 71.776,
      "duration": 0.16100000000000136
    },
    {
      "word": "think",
      "start": 71.816,
      "end": 72.056,
      "duration": 0.23999999999999488
    },
    {
      "word": "it's",
      "start": 72.076,
      "end": 72.236,
      "duration": 0.1600000000000108
    },
    {
      "word": "bigans.",
      "start": 72.276,
      "end": 72.577,
      "duration": 0.30100000000000193
    },
    {
      "word": "Did",
      "start": 72.597,
      "end": 72.657,
      "duration": 0.060000000000002274
    },
    {
      "word": "you",
      "start": 72.677,
      "end": 72.797,
      "duration": 0.11999999999999034
    },
    {
      "word": "see",
      "start": 72.817,
      "end": 72.937,
      "duration": 0.12000000000000455
    },
    {
      "word": "that",
      "start": 72.977,
      "end": 73.097,
      "duration": 0.11999999999999034
    },
    {
      "word": "fucking",
      "start": 73.158,
      "end": 73.418,
      "duration": 0.2600000000000051
    },
    {
      "word": "video",
      "start": 73.438,
      "end": 73.818,
      "duration": 0.37999999999999545
    },
    {
      "word": "that",
      "start": 73.838,
      "end": 73.939,
      "duration": 0.10099999999999909
    },
    {
      "word": "do",
      "start": 73.999,
      "end": 74.079,
      "duration": 0.0799999999999983
    },
    {
      "word": "crying?",
      "start": 74.279,
      "end": 74.68,
      "duration": 0.40100000000001046
    },
    {
      "word": "Oh",
      "start": 75.18,
      "end": 75.22,
      "duration": 0.03999999999999204
    },
    {
      "word": "the",
      "start": 75.24,
      "end": 75.381,
      "duration": 0.14100000000000534
    },
    {
      "word": "the",
      "start": 75.401,
      "end": 75.481,
      "duration": 0.0799999999999983
    },
    {
      "word": "the",
      "start": 75.541,
      "end": 75.681,
      "duration": 0.14000000000000057
    },
    {
      "word": "the",
      "start": 75.701,
      "end": 75.761,
      "duration": 0.060000000000002274
    },
    {
      "word": "the",
      "start": 75.821,
      "end": 75.921,
      "duration": 0.10000000000000853
    },
    {
      "word": "the",
      "start": 76.021,
      "end": 76.081,
      "duration": 0.060000000000002274
    },
    {
      "word": "the",
      "start": 76.101,
      "end": 76.282,
      "duration": 0.18099999999999739
    },
    {
      "word": "the",
      "start": 76.302,
      "end": 76.362,
      "duration": 0.05999999999998806
    },
    {
      "word": "the",
      "start": 76.522,
      "end": 76.602,
      "duration": 0.0799999999999983
    },
    {
      "word": "back.",
      "start": 76.642,
      "end": 76.903,
      "duration": 0.2610000000000099
    },
    {
      "word": "Oh",
      "start": 77.143,
      "end": 77.343,
      "duration": 0.20000000000000284
    },
    {
      "word": "dude",
      "start": 77.443,
      "end": 77.704,
      "duration": 0.2609999999999957
    },
    {
      "word": "dude.",
      "start": 78.104,
      "end": 78.304,
      "duration": 0.20000000000000284
    },
    {
      "word": "I",
      "start": 78.585,
      "end": 78.645,
      "duration": 0.060000000000002274
    },
    {
      "word": "thought",
      "start": 78.685,
      "end": 78.865,
      "duration": 0.1799999999999926
    },
    {
      "word": "that",
      "start": 78.905,
      "end": 79.005,
      "duration": 0.09999999999999432
    },
    {
      "word": "was",
      "start": 79.085,
      "end": 79.186,
      "duration": 0.1010000000000133
    },
    {
      "word": "like",
      "start": 79.226,
      "end": 79.346,
      "duration": 0.12000000000000455
    },
    {
      "word": "a",
      "start": 79.386,
      "end": 79.406,
      "duration": 0.020000000000010232
    },
    {
      "word": "fake.",
      "start": 79.726,
      "end": 80.047,
      "duration": 0.32099999999999795
    },
    {
      "word": "I",
      "start": 80.067,
      "end": 80.127,
      "duration": 0.060000000000002274
    },
    {
      "word": "thought",
      "start": 80.187,
      "end": 80.347,
      "duration": 0.1599999999999966
    },
    {
      "word": "it",
      "start": 80.407,
      "end": 80.447,
      "duration": 0.04000000000000625
    },
    {
      "word": "was",
      "start": 80.507,
      "end": 80.668,
      "duration": 0.16100000000000136
    },
    {
      "word": "Like",
      "start": 80.728,
      "end": 80.808,
      "duration": 0.0800000000000125
    },
    {
      "word": "six",
      "start": 80.848,
      "end": 81.108,
      "duration": 0.2600000000000051
    },
    {
      "word": "to",
      "start": 81.168,
      "end": 81.409,
      "duration": 0.24099999999999966
    },
    {
      "word": "you",
      "start": 81.429,
      "end": 81.489,
      "duration": 0.060000000000002274
    },
    {
      "word": "dude.",
      "start": 81.569,
      "end": 81.749,
      "duration": 0.1799999999999926
    },
    {
      "word": "You",
      "start": 81.769,
      "end": 81.849,
      "duration": 0.0799999999999983
    },
    {
      "word": "know",
      "start": 81.869,
      "end": 81.969,
      "duration": 0.09999999999999432
    },
    {
      "word": "what",
      "start": 82.009,
      "end": 82.109,
      "duration": 0.09999999999999432
    },
    {
      "word": "that",
      "start": 82.13,
      "end": 82.27,
      "duration": 0.14000000000000057
    },
    {
      "word": "that",
      "start": 82.31,
      "end": 82.45,
      "duration": 0.14000000000000057
    },
    {
      "word": "guy",
      "start": 82.47,
      "end": 82.63,
      "duration": 0.1599999999999966
    },
    {
      "word": "has",
      "start": 82.67,
      "end": 82.81,
      "duration": 0.14000000000000057
    },
    {
      "word": "to",
      "start": 82.83,
      "end": 82.891,
      "duration": 0.06100000000000705
    },
    {
      "word": "be",
      "start": 82.931,
      "end": 83.011,
      "duration": 0.0799999999999983
    },
    {
      "word": "a",
      "start": 83.051,
      "end": 83.071,
      "duration": 0.01999999999999602
    },
    {
      "word": "fucking",
      "start": 83.151,
      "end": 83.491,
      "duration": 0.3400000000000034
    },
    {
      "word": "influencer",
      "start": 83.752,
      "end": 84.212,
      "duration": 0.46000000000000796
    },
    {
      "word": "that",
      "start": 84.252,
      "end": 84.332,
      "duration": 0.0799999999999983
    },
    {
      "word": "they",
      "start": 84.372,
      "end": 84.493,
      "duration": 0.12099999999999511
    },
    {
      "word": "paid",
      "start": 84.533,
      "end": 84.733,
      "duration": 0.20000000000000284
    },
    {
      "word": "to",
      "start": 84.753,
      "end": 84.813,
      "duration": 0.060000000000002274
    },
    {
      "word": "do",
      "start": 84.853,
      "end": 84.953,
      "duration": 0.10000000000000853
    },
    {
      "word": "that.",
      "start": 84.973,
      "end": 85.093,
      "duration": 0.12000000000000455
    },
    {
      "word": "Yeah,",
      "start": 85.113,
      "end": 85.474,
      "duration": 0.3610000000000042
    },
    {
      "word": "there's",
      "start": 85.494,
      "end": 85.694,
      "duration": 0.20000000000000284
    },
    {
      "word": "no",
      "start": 85.754,
      "end": 85.874,
      "duration": 0.11999999999999034
    },
    {
      "word": "fucking",
      "start": 85.955,
      "end": 86.295,
      "duration": 0.3400000000000034
    },
    {
      "word": "way",
      "start": 86.355,
      "end": 90.02,
      "duration": 3.664999999999992
    },
    {
      "word": "and",
      "start": 90.0,
      "end": 90.187,
      "duration": 0.1869999999999976
    }
  ],
  "summary": {
    "stock_count": 274,
    "lightning_count": 249,
    "stock_time_range": "0.976-90.087",
    "lightning_time_range": "0.000-90.187"
  }
}